finesse/.gitignore
finesse/__init__.py
finesse/__main__.py
finesse/config.py
finesse/constants.cpython-313-x86_64-linux-gnu.so
finesse/constants.h
finesse/constants.pxd
finesse/constants.pyx
finesse/cyexpr.cpython-313-x86_64-linux-gnu.so
finesse/cyexpr.pxd
finesse/cyexpr.pyx
finesse/datastore.py
finesse/densematrix.py
finesse/element.py
finesse/element_workspace.cpython-313-x86_64-linux-gnu.so
finesse/element_workspace.pxd
finesse/element_workspace.pyx
finesse/enums.cpython-313-x86_64-linux-gnu.so
finesse/enums.pxd
finesse/enums.pyx
finesse/env.py
finesse/exceptions.py
finesse/finesse.ini
finesse/freeze.py
finesse/frequency.cpython-313-x86_64-linux-gnu.so
finesse/frequency.pxd
finesse/frequency.pyx
finesse/gaussian.py
finesse/locks.py
finesse/materials.cpython-313-x86_64-linux-gnu.so
finesse/materials.pxd
finesse/materials.pyx
finesse/model.py
finesse/numpy2_check.py
finesse/parameter.cpython-313-x86_64-linux-gnu.so
finesse/parameter.pxd
finesse/parameter.pyx
finesse/paths.py
finesse/symbols.py
finesse/tinyexpr.c
finesse/tinyexpr.h
finesse/tree.cpython-313-x86_64-linux-gnu.so
finesse/tree.pxd
finesse/tree.pyx
finesse/usr.ini.dist
finesse/version.py
finesse/warnings.py
finesse/analysis/__init__.py
finesse/analysis/beamtrace.py
finesse/analysis/noise.py
finesse/analysis/runners.cpython-313-x86_64-linux-gnu.so
finesse/analysis/runners.pyx
finesse/analysis/actions/__init__.py
finesse/analysis/actions/axes.py
finesse/analysis/actions/base.py
finesse/analysis/actions/beam.py
finesse/analysis/actions/dc.py
finesse/analysis/actions/debug.py
finesse/analysis/actions/folder.py
finesse/analysis/actions/locks.py
finesse/analysis/actions/lti.py
finesse/analysis/actions/noise.py
finesse/analysis/actions/operator.py
finesse/analysis/actions/optimisation.py
finesse/analysis/actions/parallel.py
finesse/analysis/actions/pseudolock.py
finesse/analysis/actions/random.py
finesse/analysis/actions/sensing.py
finesse-3.0a33.dist-info/LICENSE.md
finesse-3.0a33.dist-info/METADATA
finesse-3.0a33.dist-info/WHEEL
finesse-3.0a33.dist-info/entry_points.txt
finesse-3.0a33.dist-info/top_level.txt
finesse-3.0a33.dist-info/RECORD
