Metadata-Version: 2.1
Name: finesse
Version: 3.0a33
Summary: Simulation tool for modelling laser interferometers
Maintainer-email: Finesse Team <finesse-support@nikhef.nl>
License:                     GNU AFFERO GENERAL PUBLIC LICENSE
Project-URL: Homepage, https://www.gwoptics.org/finesse
Project-URL: Bug Tracker, https://gitlab.com/ifosim/finesse/finesse3/issues
Project-URL: Source Code, https://gitlab.com/ifosim/finesse/finesse3
Project-URL: Documentation, https://finesse.ifosim.org/docs/
Classifier: Development Status :: 3 - Alpha
Classifier: Topic :: Scientific/Engineering :: Physics
Classifier: Intended Audience :: Science/Research
Classifier: Natural Language :: English
Classifier: License :: OSI Approved :: GNU General Public License v3 or later (GPLv3+)
Classifier: Operating System :: Microsoft :: Windows
Classifier: Operating System :: POSIX
Classifier: Operating System :: Unix
Classifier: Operating System :: MacOS
Classifier: Programming Language :: Python :: 3
Classifier: Programming Language :: Python :: 3.10
Classifier: Programming Language :: Python :: 3.11
Classifier: Programming Language :: Python :: 3.12
Requires-Python: >=3.10
License-File: LICENSE.md
Requires-Dist: numpy>=1.20
Requires-Dist: scipy>=1.4
Requires-Dist: matplotlib>=3.5
Requires-Dist: networkx>=2.4
Requires-Dist: sly>=0.4
Requires-Dist: click>=7.1
Requires-Dist: click-default-group>=1.2.2
Requires-Dist: control>=0.9
Requires-Dist: sympy>=1.6
Requires-Dist: more-itertools>=8.7
Requires-Dist: tqdm>=4.40
Requires-Dist: h5py>=3.0
Requires-Dist: deprecated>=1.2
Requires-Dist: pyspellchecker>=0.6
Requires-Dist: quantiphy>=2.15
Requires-Dist: dill
Requires-Dist: pathos
Provides-Extra: test
Requires-Dist: pytest; extra == "test"
Requires-Dist: pytest-benchmark; extra == "test"
Requires-Dist: pytest-xdist; extra == "test"
Requires-Dist: faker; extra == "test"
Requires-Dist: hypothesis; extra == "test"
Requires-Dist: docutils; extra == "test"
Requires-Dist: black; extra == "test"
Requires-Dist: autoflake; extra == "test"
Requires-Dist: isort; extra == "test"
Requires-Dist: jupyter-sphinx>=0.4; extra == "test"
Requires-Dist: pytest-random-order; extra == "test"
Requires-Dist: pyyaml; extra == "test"
Requires-Dist: psutil; extra == "test"
Requires-Dist: cython>=0.29.36; extra == "test"
Requires-Dist: nbformat; extra == "test"
Requires-Dist: nbconvert; extra == "test"
Provides-Extra: docs
Requires-Dist: ipykernel; extra == "docs"
Requires-Dist: setuptools<=75.6.0,>=45; extra == "docs"
Requires-Dist: sphinx<6; extra == "docs"
Requires-Dist: sphinx_rtd_theme; extra == "docs"
Requires-Dist: sphinxcontrib-bibtex; extra == "docs"
Requires-Dist: sphinxcontrib-programoutput; extra == "docs"
Requires-Dist: jupyter-sphinx>=0.4; extra == "docs"
Requires-Dist: numpydoc; extra == "docs"
Requires-Dist: sphinxcontrib-katex; extra == "docs"
Requires-Dist: sphinxcontrib-svg2pdfconverter; extra == "docs"
Requires-Dist: reslate; extra == "docs"
Requires-Dist: standard-imghdr; extra == "docs"
Provides-Extra: lint
Requires-Dist: black; extra == "lint"
Requires-Dist: pre-commit; extra == "lint"
Requires-Dist: tox; extra == "lint"
Requires-Dist: flake8; extra == "lint"
Requires-Dist: flake8-bugbear; extra == "lint"
Requires-Dist: doc8; extra == "lint"
Requires-Dist: cython-lint; extra == "lint"
Provides-Extra: inplacebuild
Requires-Dist: setuptools<=75.6.0,>=45; extra == "inplacebuild"
Requires-Dist: setuptools_scm>=8.0.3; extra == "inplacebuild"
Requires-Dist: wheel; extra == "inplacebuild"
Requires-Dist: numpy>=1.20; extra == "inplacebuild"
Requires-Dist: cython>=0.29.36; extra == "inplacebuild"
Requires-Dist: scipy>=1.4; extra == "inplacebuild"
Requires-Dist: tqdm>=4.40; extra == "inplacebuild"
Provides-Extra: graphviz
Requires-Dist: pygraphviz; extra == "graphviz"
